{
  "batch_info": {
    "batch_id": 2,
    "experiment_type": "baseline",
    "batch_size": 200,
    "start_time": "2025-10-14T18:30:32.621002",
    "processed_samples": 200,
    "error_count": 0,
    "current_sample_idx": 199,
    "estimated_completion_time": null,
    "status": "completed",
    "last_update": "2025-10-14T18:35:41.673420",
    "elapsed_time": 309.05469489097595,
    "completion_time": 309.06240582466125,
    "completion_timestamp": "2025-10-14T18:35:41.681152"
  },
  "summary": {
    "total_samples": 200,
    "baseline_only": {
      "avg_context_precision": 0.07844194262558223,
      "avg_faithfulness": 0.301100089355872,
      "avg_answer_relevancy": 0.3442571501472683,
      "avg_context_recall": 0.19509578456278953
    }
  },
  "results": [
    {
      "context_precision": 0.07742326204060816,
      "faithfulness": 0.0,
      "answer_relevancy": 0.0625,
      "context_recall": 0.18340611353711792
    },
    {
      "context_precision": 0.047161237183674626,
      "faithfulness": 0.3333333333333333,
      "answer_relevancy": 0.3,
      "context_recall": 0.13813229571984437
    },
    {
      "context_precision": 0.07549488458862023,
      "faithfulness": 0.6451612903225806,
      "answer_relevancy": 0.6666666666666666,
      "context_recall": 0.21095334685598377
    },
    {
      "context_precision": 0.057857449549162734,
      "faithfulness": 0.4375,
      "answer_relevancy": 0.8181818181818182,
      "context_recall": 0.15257352941176472
    },
    {
      "context_precision": 0.05286571934522524,
      "faithfulness": 0.25,
      "answer_relevancy": 0.09090909090909091,
      "context_recall": 0.1301775147928994
    },
    {
      "context_precision": 0.0846475023279565,
      "faithfulness": 0.5,
      "answer_relevancy": 0.08333333333333333,
      "context_recall": 0.20164609053497942
    },
    {
      "context_precision": 0.07216981850875455,
      "faithfulness": 0.5,
      "answer_relevancy": 0.8181818181818182,
      "context_recall": 0.1941544885177453
    },
    {
      "context_precision": 0.07604782508174522,
      "faithfulness": 0.0,
      "answer_relevancy": 0.09523809523809523,
      "context_recall": 0.22624434389140272
    },
    {
      "context_precision": 0.544537919089447,
      "faithfulness": 0.36363636363636365,
      "answer_relevancy": 0.3333333333333333,
      "context_recall": 1.0
    },
    {
      "context_precision": 0.10569145788123892,
      "faithfulness": 0.6666666666666666,
      "answer_relevancy": 0.8461538461538461,
      "context_recall": 0.24774774774774774
    },
    {
      "context_precision": 0.05861345195952509,
      "faithfulness": 0.6470588235294118,
      "answer_relevancy": 0.75,
      "context_recall": 0.16952789699570817
    },
    {
      "context_precision": 0.053779908112730965,
      "faithfulness": 0.0,
      "answer_relevancy": 0.0,
      "context_recall": 0.16212534059945505
    },
    {
      "context_precision": 0.07226537132763591,
      "faithfulness": 0.5789473684210527,
      "answer_relevancy": 0.8,
      "context_recall": 0.17437722419928825
    },
    {
      "context_precision": 0.058994100589941006,
      "faithfulness": 0.0,
      "answer_relevancy": 0.0,
      "context_recall": 0.17294520547945205
    },
    {
      "context_precision": 0.055085158150851576,
      "faithfulness": 0.631578947368421,
      "answer_relevancy": 0.8823529411764706,
      "context_recall": 0.14166666666666666
    },
    {
      "context_precision": 0.08049679725904961,
      "faithfulness": 0.6875,
      "answer_relevancy": 0.8333333333333334,
      "context_recall": 0.20408163265306123
    },
    {
      "context_precision": 0.058578485585784865,
      "faithfulness": 0.6086956521739131,
      "answer_relevancy": 0.875,
      "context_recall": 0.13383838383838384
    },
    {
      "context_precision": 0.08238120731755091,
      "faithfulness": 1.0,
      "answer_relevancy": 0.26666666666666666,
      "context_recall": 0.22898032200357782
    },
    {
      "context_precision": 0.10717873166811759,
      "faithfulness": 0.2857142857142857,
      "answer_relevancy": 0.20833333333333334,
      "context_recall": 0.25688073394495414
    },
    {
      "context_precision": 0.07462561583229824,
      "faithfulness": 0.47058823529411764,
      "answer_relevancy": 0.8666666666666667,
      "context_recall": 0.17782026768642448
    },
    {
      "context_precision": 0.06279545742696203,
      "faithfulness": 0.0,
      "answer_relevancy": 0.07142857142857142,
      "context_recall": 0.2109181141439206
    },
    {
      "context_precision": 0.09067878461611541,
      "faithfulness": 0.0,
      "answer_relevancy": 0.0,
      "context_recall": 0.2386117136659436
    },
    {
      "context_precision": 0.0770822471324296,
      "faithfulness": 0.0,
      "answer_relevancy": 0.06666666666666667,
      "context_recall": 0.20089285714285715
    },
    {
      "context_precision": 0.07468717413972889,
      "faithfulness": 0.46153846153846156,
      "answer_relevancy": 0.7142857142857143,
      "context_recall": 0.18154761904761904
    },
    {
      "context_precision": 0.07098008645737368,
      "faithfulness": 0.6,
      "answer_relevancy": 0.3333333333333333,
      "context_recall": 0.18058252427184465
    },
    {
      "context_precision": 0.06852598322257326,
      "faithfulness": 0.0,
      "answer_relevancy": 0.0,
      "context_recall": 0.166044776119403
    },
    {
      "context_precision": 0.059803988448507164,
      "faithfulness": 0.4166666666666667,
      "answer_relevancy": 0.6470588235294118,
      "context_recall": 0.20249221183800623
    },
    {
      "context_precision": 0.10719908401316733,
      "faithfulness": 0.631578947368421,
      "answer_relevancy": 0.875,
      "context_recall": 0.2222222222222222
    },
    {
      "context_precision": 0.07429257074292571,
      "faithfulness": 0.6923076923076923,
      "answer_relevancy": 0.8333333333333334,
      "context_recall": 0.18082191780821918
    },
    {
      "context_precision": 0.07408563956438581,
      "faithfulness": 0.8,
      "answer_relevancy": 0.8333333333333334,
      "context_recall": 0.20499108734402852
    },
    {
      "context_precision": 0.061600878747076745,
      "faithfulness": 0.0,
      "answer_relevancy": 0.0,
      "context_recall": 0.1650485436893204
    },
    {
      "context_precision": 0.07237931669017973,
      "faithfulness": 0.0,
      "answer_relevancy": 0.0,
      "context_recall": 0.17366946778711484
    },
    {
      "context_precision": 0.07416703124640217,
      "faithfulness": 0.0,
      "answer_relevancy": 0.14285714285714285,
      "context_recall": 0.1608832807570978
    },
    {
      "context_precision": 0.0816251708162517,
      "faithfulness": 0.35714285714285715,
      "answer_relevancy": 0.6111111111111112,
      "context_recall": 0.18493150684931506
    },
    {
      "context_precision": 0.035123941848743574,
      "faithfulness": 0.4,
      "answer_relevancy": 0.15789473684210525,
      "context_recall": 0.09317803660565724
    },
    {
      "context_precision": 0.08551555390600302,
      "faithfulness": 0.0,
      "answer_relevancy": 0.0,
      "context_recall": 0.19397363465160075
    },
    {
      "context_precision": 0.0442408407634357,
      "faithfulness": 0.0,
      "answer_relevancy": 0.18181818181818182,
      "context_recall": 0.11235955056179775
    },
    {
      "context_precision": 0.12333508917149523,
      "faithfulness": 0.6756756756756757,
      "answer_relevancy": 0.8636363636363636,
      "context_recall": 0.3582474226804124
    },
    {
      "context_precision": 0.09079152144845574,
      "faithfulness": 0.0,
      "answer_relevancy": 0.0,
      "context_recall": 0.1981981981981982
    },
    {
      "context_precision": 0.08315553060078608,
      "faithfulness": 0.0,
      "answer_relevancy": 0.0,
      "context_recall": 0.19487179487179487
    },
    {
      "context_precision": 0.05296350364963504,
      "faithfulness": 0.0,
      "answer_relevancy": 0.0,
      "context_recall": 0.16533333333333333
    },
    {
      "context_precision": 0.09340215653055087,
      "faithfulness": 0.4,
      "answer_relevancy": 0.21428571428571427,
      "context_recall": 0.19305856832971802
    },
    {
      "context_precision": 0.09772997330288112,
      "faithfulness": 1.0,
      "answer_relevancy": 0.0,
      "context_recall": 0.2769556025369979
    },
    {
      "context_precision": 0.06389431479387274,
      "faithfulness": 0.0,
      "answer_relevancy": 0.0,
      "context_recall": 0.16666666666666666
    },
    {
      "context_precision": 0.12778228350004509,
      "faithfulness": 0.7058823529411765,
      "answer_relevancy": 0.8666666666666667,
      "context_recall": 0.29218106995884774
    },
    {
      "context_precision": 0.07287900493439753,
      "faithfulness": 0.0,
      "answer_relevancy": 0.13333333333333333,
      "context_recall": 0.1838006230529595
    },
    {
      "context_precision": 0.15566117806823968,
      "faithfulness": 0.0,
      "answer_relevancy": 0.0,
      "context_recall": 0.3798449612403101
    },
    {
      "context_precision": 0.05769596953348144,
      "faithfulness": 0.6666666666666666,
      "answer_relevancy": 0.47058823529411764,
      "context_recall": 0.14492753623188406
    },
    {
      "context_precision": 0.10126552279836952,
      "faithfulness": 0.5384615384615384,
      "answer_relevancy": 0.8,
      "context_recall": 0.237012987012987
    },
    {
      "context_precision": 0.04635159379684927,
      "faithfulness": 0.0,
      "answer_relevancy": 0.0,
      "context_recall": 0.1111111111111111
    },
    {
      "context_precision": 0.09622182435844467,
      "faithfulness": 0.0,
      "answer_relevancy": 0.0,
      "context_recall": 0.2389937106918239
    },
    {
      "context_precision": 0.0820783711102574,
      "faithfulness": 0.0,
      "answer_relevancy": 0.0,
      "context_recall": 0.2131578947368421
    },
    {
      "context_precision": 0.07211327060065079,
      "faithfulness": 0.3333333333333333,
      "answer_relevancy": 0.05,
      "context_recall": 0.1783132530120482
    },
    {
      "context_precision": 0.06224076005097904,
      "faithfulness": 0.0,
      "answer_relevancy": 0.0,
      "context_recall": 0.14285714285714285
    },
    {
      "context_precision": 0.058720993572284566,
      "faithfulness": 0.0,
      "answer_relevancy": 0.0,
      "context_recall": 0.1513859275053305
    },
    {
      "context_precision": 0.050335237969415726,
      "faithfulness": 0.0,
      "answer_relevancy": 0.05555555555555555,
      "context_recall": 0.1515837104072398
    },
    {
      "context_precision": 0.06694729300076127,
      "faithfulness": 0.8,
      "answer_relevancy": 0.7,
      "context_recall": 0.19938650306748465
    },
    {
      "context_precision": 0.08195330588006576,
      "faithfulness": 0.0,
      "answer_relevancy": 0.0,
      "context_recall": 0.1937046004842615
    },
    {
      "context_precision": 0.10373522908295489,
      "faithfulness": 0.45,
      "answer_relevancy": 0.8666666666666667,
      "context_recall": 0.250814332247557
    },
    {
      "context_precision": 0.04301971377665383,
      "faithfulness": 0.8125,
      "answer_relevancy": 0.8,
      "context_recall": 0.14173228346456693
    },
    {
      "context_precision": 0.07397293843757112,
      "faithfulness": 0.35714285714285715,
      "answer_relevancy": 0.7692307692307693,
      "context_recall": 0.1630695443645084
    },
    {
      "context_precision": 0.10581879665140832,
      "faithfulness": 0.7407407407407407,
      "answer_relevancy": 0.85,
      "context_recall": 0.22033898305084745
    },
    {
      "context_precision": 0.11085646052808967,
      "faithfulness": 0.0,
      "answer_relevancy": 0.0,
      "context_recall": 0.2612137203166227
    },
    {
      "context_precision": 0.08792592356484875,
      "faithfulness": 0.3333333333333333,
      "answer_relevancy": 0.07692307692307693,
      "context_recall": 0.2292576419213974
    },
    {
      "context_precision": 0.04247055732611403,
      "faithfulness": 0.0,
      "answer_relevancy": 0.0,
      "context_recall": 0.13458528951486698
    },
    {
      "context_precision": 0.058187876864487474,
      "faithfulness": 0.7142857142857143,
      "answer_relevancy": 0.75,
      "context_recall": 0.1608695652173913
    },
    {
      "context_precision": 0.061332116788321185,
      "faithfulness": 0.0,
      "answer_relevancy": 0.0,
      "context_recall": 0.125
    },
    {
      "context_precision": 0.06265756787793192,
      "faithfulness": 0.5,
      "answer_relevancy": 0.8181818181818182,
      "context_recall": 0.16455696202531644
    },
    {
      "context_precision": 0.030294356185296505,
      "faithfulness": 0.5,
      "answer_relevancy": 0.875,
      "context_recall": 0.13071895424836602
    },
    {
      "context_precision": 0.14417939649334036,
      "faithfulness": 0.3333333333333333,
      "answer_relevancy": 0.05263157894736842,
      "context_recall": 0.3402061855670103
    },
    {
      "context_precision": 0.08833137665254455,
      "faithfulness": 0.42857142857142855,
      "answer_relevancy": 0.3333333333333333,
      "context_recall": 0.19230769230769232
    },
    {
      "context_precision": 0.07835463102483319,
      "faithfulness": 0.3333333333333333,
      "answer_relevancy": 0.46153846153846156,
      "context_recall": 0.16085790884718498
    },
    {
      "context_precision": 0.05459950693672356,
      "faithfulness": 0.0,
      "answer_relevancy": 0.0,
      "context_recall": 0.18543046357615894
    },
    {
      "context_precision": 0.06579830522694857,
      "faithfulness": 0.0,
      "answer_relevancy": 0.0,
      "context_recall": 0.14655172413793102
    },
    {
      "context_precision": 0.13463866883453834,
      "faithfulness": 0.7777777777777778,
      "answer_relevancy": 0.5,
      "context_recall": 0.3080568720379147
    },
    {
      "context_precision": 0.06593275098719636,
      "faithfulness": 0.0,
      "answer_relevancy": 0.07142857142857142,
      "context_recall": 0.1540983606557377
    },
    {
      "context_precision": 0.07925191936764872,
      "faithfulness": 0.7391304347826086,
      "answer_relevancy": 0.8666666666666667,
      "context_recall": 0.18911917098445596
    },
    {
      "context_precision": 0.0554488410808042,
      "faithfulness": 0.0,
      "answer_relevancy": 0.0,
      "context_recall": 0.13157894736842105
    },
    {
      "context_precision": 0.09375550380618773,
      "faithfulness": 0.0,
      "answer_relevancy": 0.0,
      "context_recall": 0.1876675603217158
    },
    {
      "context_precision": 0.0952829448237972,
      "faithfulness": 0.14285714285714285,
      "answer_relevancy": 0.11764705882352941,
      "context_recall": 0.26881720430107525
    },
    {
      "context_precision": 0.07452098540145986,
      "faithfulness": 0.4074074074074074,
      "answer_relevancy": 0.85,
      "context_recall": 0.20625
    },
    {
      "context_precision": 0.09961826574454152,
      "faithfulness": 0.0,
      "answer_relevancy": 0.0,
      "context_recall": 0.23413566739606126
    },
    {
      "context_precision": 0.06124494846652674,
      "faithfulness": 0.3333333333333333,
      "answer_relevancy": 0.26666666666666666,
      "context_recall": 0.15021459227467812
    },
    {
      "context_precision": 0.09415461723582409,
      "faithfulness": 0.5833333333333334,
      "answer_relevancy": 0.8181818181818182,
      "context_recall": 0.23160762942779292
    },
    {
      "context_precision": 0.1369541012000495,
      "faithfulness": 0.5384615384615384,
      "answer_relevancy": 0.375,
      "context_recall": 0.2966101694915254
    },
    {
      "context_precision": 0.06813040740654369,
      "faithfulness": 0.9523809523809523,
      "answer_relevancy": 0.42105263157894735,
      "context_recall": 0.17731629392971246
    },
    {
      "context_precision": 0.5222545414631469,
      "faithfulness": 0.7380952380952381,
      "answer_relevancy": 0.782608695652174,
      "context_recall": 1.0
    },
    {
      "context_precision": 0.0506002787811568,
      "faithfulness": 0.0,
      "answer_relevancy": 0.0,
      "context_recall": 0.1437371663244353
    },
    {
      "context_precision": 0.05658106566217041,
      "faithfulness": 0.0,
      "answer_relevancy": 0.0,
      "context_recall": 0.14346895074946467
    },
    {
      "context_precision": 0.04833792827040091,
      "faithfulness": 0.0,
      "answer_relevancy": 0.0,
      "context_recall": 0.15474209650582363
    },
    {
      "context_precision": 0.06475240977644396,
      "faithfulness": 0.0,
      "answer_relevancy": 0.0,
      "context_recall": 0.16898954703832753
    },
    {
      "context_precision": 0.07654970543554783,
      "faithfulness": 0.0,
      "answer_relevancy": 0.21428571428571427,
      "context_recall": 0.14720812182741116
    },
    {
      "context_precision": 0.07776741122880193,
      "faithfulness": 0.3333333333333333,
      "answer_relevancy": 0.6923076923076923,
      "context_recall": 0.17293233082706766
    },
    {
      "context_precision": 0.04369742397957514,
      "faithfulness": 0.0,
      "answer_relevancy": 0.0,
      "context_recall": 0.14798206278026907
    },
    {
      "context_precision": 0.05649595898319015,
      "faithfulness": 0.25,
      "answer_relevancy": 0.07692307692307693,
      "context_recall": 0.16621983914209115
    },
    {
      "context_precision": 0.10074596935910804,
      "faithfulness": 0.0,
      "answer_relevancy": 0.0,
      "context_recall": 0.26373626373626374
    },
    {
      "context_precision": 0.07888873844487389,
      "faithfulness": 0.0,
      "answer_relevancy": 0.07692307692307693,
      "context_recall": 0.1821247892074199
    },
    {
      "context_precision": 0.07767706745808936,
      "faithfulness": 0.5652173913043478,
      "answer_relevancy": 0.6666666666666666,
      "context_recall": 0.2021978021978022
    },
    {
      "context_precision": 0.029540788176448778,
      "faithfulness": 0.75,
      "answer_relevancy": 0.9523809523809523,
      "context_recall": 0.09045848822800495
    },
    {
      "context_precision": 0.04512137512762294,
      "faithfulness": 0.0,
      "answer_relevancy": 0.07692307692307693,
      "context_recall": 0.1336116910229645
    },
    {
      "context_precision": 0.07936014909147383,
      "faithfulness": 0.0,
      "answer_relevancy": 0.0,
      "context_recall": 0.21513002364066194
    },
    {
      "context_precision": 0.07116262437156862,
      "faithfulness": 0.0,
      "answer_relevancy": 0.0,
      "context_recall": 0.15561959654178675
    },
    {
      "context_precision": 0.05204379562043796,
      "faithfulness": 0.0,
      "answer_relevancy": 0.0,
      "context_recall": 0.1225
    },
    {
      "context_precision": 0.0710019907100199,
      "faithfulness": 0.0,
      "answer_relevancy": 0.0,
      "context_recall": 0.18434343434343434
    },
    {
      "context_precision": 0.05750588962267794,
      "faithfulness": 0.0,
      "answer_relevancy": 0.0,
      "context_recall": 0.14285714285714285
    },
    {
      "context_precision": 0.11964540811334418,
      "faithfulness": 0.0,
      "answer_relevancy": 0.0,
      "context_recall": 0.2707774798927614
    },
    {
      "context_precision": 0.0689168875044555,
      "faithfulness": 0.0,
      "answer_relevancy": 0.15384615384615385,
      "context_recall": 0.15286624203821655
    },
    {
      "context_precision": 0.06813627254509018,
      "faithfulness": 0.0,
      "answer_relevancy": 0.0,
      "context_recall": 0.18036072144288579
    },
    {
      "context_precision": 0.03311991257688051,
      "faithfulness": 0.6363636363636364,
      "answer_relevancy": 0.5384615384615384,
      "context_recall": 0.12092130518234165
    },
    {
      "context_precision": 0.08112694265628789,
      "faithfulness": 0.0,
      "answer_relevancy": 0.0,
      "context_recall": 0.2066420664206642
    },
    {
      "context_precision": 0.04124624302275655,
      "faithfulness": 0.0,
      "answer_relevancy": 0.0,
      "context_recall": 0.12867647058823528
    },
    {
      "context_precision": 0.09129863992018064,
      "faithfulness": 0.6,
      "answer_relevancy": 0.07142857142857142,
      "context_recall": 0.25611510791366904
    },
    {
      "context_precision": 0.06096659056561305,
      "faithfulness": 0.16666666666666666,
      "answer_relevancy": 0.21428571428571427,
      "context_recall": 0.15418502202643172
    },
    {
      "context_precision": 0.09308307264511646,
      "faithfulness": 0.5294117647058824,
      "answer_relevancy": 0.75,
      "context_recall": 0.22857142857142856
    },
    {
      "context_precision": 0.10189336396309606,
      "faithfulness": 0.7419354838709677,
      "answer_relevancy": 0.9230769230769231,
      "context_recall": 0.24619289340101522
    },
    {
      "context_precision": 0.07049417307657987,
      "faithfulness": 0.5555555555555556,
      "answer_relevancy": 0.875,
      "context_recall": 0.18337408312958436
    },
    {
      "context_precision": 0.031263626884064845,
      "faithfulness": 0.0,
      "answer_relevancy": 0.0,
      "context_recall": 0.09090909090909091
    },
    {
      "context_precision": 0.05596940305969403,
      "faithfulness": 0.16666666666666666,
      "answer_relevancy": 0.06666666666666667,
      "context_recall": 0.17123287671232876
    },
    {
      "context_precision": 0.06412102553916944,
      "faithfulness": 0.0,
      "answer_relevancy": 0.0,
      "context_recall": 0.18140589569160998
    },
    {
      "context_precision": 0.04387875563240943,
      "faithfulness": 0.2222222222222222,
      "answer_relevancy": 0.5333333333333333,
      "context_recall": 0.12300683371298406
    },
    {
      "context_precision": 0.11228451622922815,
      "faithfulness": 0.0,
      "answer_relevancy": 0.07692307692307693,
      "context_recall": 0.2576832151300236
    },
    {
      "context_precision": 0.04977772899401789,
      "faithfulness": 0.0,
      "answer_relevancy": 0.0,
      "context_recall": 0.15413533834586465
    },
    {
      "context_precision": 0.05956204379562043,
      "faithfulness": 0.0,
      "answer_relevancy": 0.0,
      "context_recall": 0.12761904761904763
    },
    {
      "context_precision": 0.07459453555891295,
      "faithfulness": 0.0,
      "answer_relevancy": 0.047619047619047616,
      "context_recall": 0.16957605985037408
    },
    {
      "context_precision": 0.12163654483260163,
      "faithfulness": 0.7142857142857143,
      "answer_relevancy": 0.8,
      "context_recall": 0.28413284132841327
    },
    {
      "context_precision": 0.06886536477242329,
      "faithfulness": 0.6,
      "answer_relevancy": 0.72,
      "context_recall": 0.18848167539267016
    },
    {
      "context_precision": 0.11604305034961968,
      "faithfulness": 0.25,
      "answer_relevancy": 0.058823529411764705,
      "context_recall": 0.2972972972972973
    },
    {
      "context_precision": 0.050392378602515345,
      "faithfulness": 0.0,
      "answer_relevancy": 0.0,
      "context_recall": 0.12441314553990611
    },
    {
      "context_precision": 0.07425904583030976,
      "faithfulness": 0.0,
      "answer_relevancy": 0.0,
      "context_recall": 0.18518518518518517
    },
    {
      "context_precision": 0.0680750267124963,
      "faithfulness": 0.6666666666666666,
      "answer_relevancy": 0.9545454545454546,
      "context_recall": 0.16225749559082892
    },
    {
      "context_precision": 0.059606406850481033,
      "faithfulness": 0.0,
      "answer_relevancy": 0.0,
      "context_recall": 0.13604240282685512
    },
    {
      "context_precision": 0.04828934743796836,
      "faithfulness": 0.0,
      "answer_relevancy": 0.18181818181818182,
      "context_recall": 0.12479201331114809
    },
    {
      "context_precision": 0.07003738650525192,
      "faithfulness": 0.5625,
      "answer_relevancy": 0.8461538461538461,
      "context_recall": 0.18048780487804877
    },
    {
      "context_precision": 0.09489051094890509,
      "faithfulness": 0.0,
      "answer_relevancy": 0.0,
      "context_recall": 0.20512820512820512
    },
    {
      "context_precision": 0.059617990296778715,
      "faithfulness": 0.6363636363636364,
      "answer_relevancy": 0.9411764705882353,
      "context_recall": 0.15568862275449102
    },
    {
      "context_precision": 0.05853753910323254,
      "faithfulness": 0.0,
      "answer_relevancy": 0.07142857142857142,
      "context_recall": 0.12678571428571428
    },
    {
      "context_precision": 0.07521882666505134,
      "faithfulness": 0.0,
      "answer_relevancy": 0.15384615384615385,
      "context_recall": 0.1950207468879668
    },
    {
      "context_precision": 0.0571586493911856,
      "faithfulness": 0.2222222222222222,
      "answer_relevancy": 0.38461538461538464,
      "context_recall": 0.14253897550111358
    },
    {
      "context_precision": 0.059088105273979646,
      "faithfulness": 0.5625,
      "answer_relevancy": 0.8461538461538461,
      "context_recall": 0.1602112676056338
    },
    {
      "context_precision": 0.07024051693191338,
      "faithfulness": 0.6,
      "answer_relevancy": 0.2857142857142857,
      "context_recall": 0.1680327868852459
    },
    {
      "context_precision": 0.06468198445744339,
      "faithfulness": 0.6923076923076923,
      "answer_relevancy": 0.8333333333333334,
      "context_recall": 0.17782909930715934
    },
    {
      "context_precision": 0.05237965300043204,
      "faithfulness": 0.0,
      "answer_relevancy": 0.0,
      "context_recall": 0.14953271028037382
    },
    {
      "context_precision": 0.05375188452524891,
      "faithfulness": 0.75,
      "answer_relevancy": 0.375,
      "context_recall": 0.1492842535787321
    },
    {
      "context_precision": 0.03471753664969637,
      "faithfulness": 0.0,
      "answer_relevancy": 0.07142857142857142,
      "context_recall": 0.11869747899159663
    },
    {
      "context_precision": 0.07082310202159509,
      "faithfulness": 0.0,
      "answer_relevancy": 0.058823529411764705,
      "context_recall": 0.16359447004608296
    },
    {
      "context_precision": 0.09609066047573141,
      "faithfulness": 0.5,
      "answer_relevancy": 0.7,
      "context_recall": 0.22371967654986524
    },
    {
      "context_precision": 0.04934717795826051,
      "faithfulness": 0.5789473684210527,
      "answer_relevancy": 0.8823529411764706,
      "context_recall": 0.14788732394366197
    },
    {
      "context_precision": 0.04973457199734571,
      "faithfulness": 0.7619047619047619,
      "answer_relevancy": 0.8823529411764706,
      "context_recall": 0.15
    },
    {
      "context_precision": 0.09817709328543586,
      "faithfulness": 0.5789473684210527,
      "answer_relevancy": 0.8571428571428571,
      "context_recall": 0.22251308900523561
    },
    {
      "context_precision": 0.06853994266311532,
      "faithfulness": 0.0,
      "answer_relevancy": 0.0,
      "context_recall": 0.17827298050139276
    },
    {
      "context_precision": 0.07073121403224916,
      "faithfulness": 0.5454545454545454,
      "answer_relevancy": 0.4666666666666667,
      "context_recall": 0.17632241813602015
    },
    {
      "context_precision": 0.03968170010696194,
      "faithfulness": 0.5652173913043478,
      "answer_relevancy": 0.8421052631578947,
      "context_recall": 0.10628019323671498
    },
    {
      "context_precision": 0.09809342391395964,
      "faithfulness": 0.6296296296296297,
      "answer_relevancy": 0.9523809523809523,
      "context_recall": 0.2586605080831409
    },
    {
      "context_precision": 0.07283983643520466,
      "faithfulness": 0.0,
      "answer_relevancy": 0.0,
      "context_recall": 0.17015706806282724
    },
    {
      "context_precision": 0.045930884090014244,
      "faithfulness": 0.0,
      "answer_relevancy": 0.0,
      "context_recall": 0.12033195020746888
    },
    {
      "context_precision": 0.06761778367617782,
      "faithfulness": 0.0,
      "answer_relevancy": 0.0,
      "context_recall": 0.16136363636363638
    },
    {
      "context_precision": 0.09370684553166304,
      "faithfulness": 0.6,
      "answer_relevancy": 0.8666666666666667,
      "context_recall": 0.22661122661122662
    },
    {
      "context_precision": 0.08584112348999018,
      "faithfulness": 0.5,
      "answer_relevancy": 0.5,
      "context_recall": 0.2046783625730994
    },
    {
      "context_precision": 0.08273452810360987,
      "faithfulness": 0.0,
      "answer_relevancy": 0.0,
      "context_recall": 0.2237354085603113
    },
    {
      "context_precision": 0.07081271738597954,
      "faithfulness": 0.0,
      "answer_relevancy": 0.0,
      "context_recall": 0.18959731543624161
    },
    {
      "context_precision": 0.14288482656159163,
      "faithfulness": 0.0,
      "answer_relevancy": 0.0,
      "context_recall": 0.30973451327433627
    },
    {
      "context_precision": 0.10164139026511858,
      "faithfulness": 0.25,
      "answer_relevancy": 0.0,
      "context_recall": 0.22279792746113988
    },
    {
      "context_precision": 0.058342636324602834,
      "faithfulness": 0.7368421052631579,
      "answer_relevancy": 0.7272727272727273,
      "context_recall": 0.1388235294117647
    },
    {
      "context_precision": 0.10848756812973057,
      "faithfulness": 0.9444444444444444,
      "answer_relevancy": 0.34782608695652173,
      "context_recall": 0.2638522427440633
    },
    {
      "context_precision": 0.04517698767757633,
      "faithfulness": 0.0,
      "answer_relevancy": 0.0,
      "context_recall": 0.11612903225806452
    },
    {
      "context_precision": 0.03158503711180315,
      "faithfulness": 0.4,
      "answer_relevancy": 0.48,
      "context_recall": 0.13490725126475547
    },
    {
      "context_precision": 0.08056828386561976,
      "faithfulness": 0.0,
      "answer_relevancy": 0.06666666666666667,
      "context_recall": 0.19873817034700317
    },
    {
      "context_precision": 0.10575040056969914,
      "faithfulness": 0.6923076923076923,
      "answer_relevancy": 0.7142857142857143,
      "context_recall": 0.24390243902439024
    },
    {
      "context_precision": 0.07031133621331745,
      "faithfulness": 0.5,
      "answer_relevancy": 0.05263157894736842,
      "context_recall": 0.18075801749271136
    },
    {
      "context_precision": 0.07029514439860361,
      "faithfulness": 0.0,
      "answer_relevancy": 0.0,
      "context_recall": 0.1826086956521739
    },
    {
      "context_precision": 0.08206702057067022,
      "faithfulness": 0.7619047619047619,
      "answer_relevancy": 0.8333333333333334,
      "context_recall": 0.18636363636363637
    },
    {
      "context_precision": 0.09305392041441017,
      "faithfulness": 0.7647058823529411,
      "answer_relevancy": 0.7142857142857143,
      "context_recall": 0.24516129032258063
    },
    {
      "context_precision": 0.08155046564309087,
      "faithfulness": 0.7222222222222222,
      "answer_relevancy": 0.8,
      "context_recall": 0.24367816091954023
    },
    {
      "context_precision": 0.12141814389989572,
      "faithfulness": 0.4444444444444444,
      "answer_relevancy": 0.8571428571428571,
      "context_recall": 0.24857142857142858
    },
    {
      "context_precision": 0.07170097596981875,
      "faithfulness": 0.47619047619047616,
      "answer_relevancy": 0.8823529411764706,
      "context_recall": 0.17415730337078653
    },
    {
      "context_precision": 0.07284220031605088,
      "faithfulness": 0.6666666666666666,
      "answer_relevancy": 0.5833333333333334,
      "context_recall": 0.17525773195876287
    },
    {
      "context_precision": 0.057020006501374156,
      "faithfulness": 0.375,
      "answer_relevancy": 0.5454545454545454,
      "context_recall": 0.17408906882591094
    },
    {
      "context_precision": 0.1304036943244451,
      "faithfulness": 0.0,
      "answer_relevancy": 0.0,
      "context_recall": 0.2857142857142857
    },
    {
      "context_precision": 0.055778588807785884,
      "faithfulness": 0.5625,
      "answer_relevancy": 0.8,
      "context_recall": 0.15416666666666667
    },
    {
      "context_precision": 0.06219714163037478,
      "faithfulness": 0.0,
      "answer_relevancy": 0.0,
      "context_recall": 0.1568627450980392
    },
    {
      "context_precision": 0.08151939725526554,
      "faithfulness": 0.0,
      "answer_relevancy": 0.0,
      "context_recall": 0.2039355992844365
    },
    {
      "context_precision": 0.05996712677400541,
      "faithfulness": 0.25,
      "answer_relevancy": 0.21739130434782608,
      "context_recall": 0.1791767554479419
    },
    {
      "context_precision": 0.10187043795620437,
      "faithfulness": 0.0,
      "answer_relevancy": 0.0,
      "context_recall": 0.36666666666666664
    },
    {
      "context_precision": 0.08849911028797618,
      "faithfulness": 0.5833333333333334,
      "answer_relevancy": 0.8333333333333334,
      "context_recall": 0.20149253731343283
    },
    {
      "context_precision": 0.08547829427583557,
      "faithfulness": 0.5333333333333333,
      "answer_relevancy": 0.625,
      "context_recall": 0.21578947368421053
    },
    {
      "context_precision": 0.05613121671515833,
      "faithfulness": 0.0,
      "answer_relevancy": 0.23076923076923078,
      "context_recall": 0.13286713286713286
    },
    {
      "context_precision": 0.07531458919921537,
      "faithfulness": 0.0,
      "answer_relevancy": 0.0,
      "context_recall": 0.20292504570383912
    },
    {
      "context_precision": 0.06029588612020025,
      "faithfulness": 0.6,
      "answer_relevancy": 0.7333333333333333,
      "context_recall": 0.13218390804597702
    },
    {
      "context_precision": 0.10177752988820718,
      "faithfulness": 0.7222222222222222,
      "answer_relevancy": 0.9333333333333333,
      "context_recall": 0.23920265780730898
    },
    {
      "context_precision": 0.07097686667858828,
      "faithfulness": 0.0,
      "answer_relevancy": 0.0,
      "context_recall": 0.1492204899777283
    },
    {
      "context_precision": 0.08393037619314991,
      "faithfulness": 0.0,
      "answer_relevancy": 0.0,
      "context_recall": 0.23846153846153847
    },
    {
      "context_precision": 0.028878261599127448,
      "faithfulness": 0.5263157894736842,
      "answer_relevancy": 0.6666666666666666,
      "context_recall": 0.09655172413793103
    },
    {
      "context_precision": 0.051878554475840756,
      "faithfulness": 0.0,
      "answer_relevancy": 0.23076923076923078,
      "context_recall": 0.12883435582822086
    },
    {
      "context_precision": 0.08497822486658897,
      "faithfulness": 0.7857142857142857,
      "answer_relevancy": 0.9615384615384616,
      "context_recall": 0.24201680672268908
    },
    {
      "context_precision": 0.06386861313868615,
      "faithfulness": 0.4166666666666667,
      "answer_relevancy": 0.6666666666666666,
      "context_recall": 0.14678899082568808
    },
    {
      "context_precision": 0.06406449750505176,
      "faithfulness": 0.0,
      "answer_relevancy": 0.0,
      "context_recall": 0.192090395480226
    },
    {
      "context_precision": 0.07449770486868841,
      "faithfulness": 0.5,
      "answer_relevancy": 0.8666666666666667,
      "context_recall": 0.19175257731958764
    },
    {
      "context_precision": 0.0644975927939121,
      "faithfulness": 0.4,
      "answer_relevancy": 0.18181818181818182,
      "context_recall": 0.19361702127659575
    },
    {
      "context_precision": 0.04883921330089214,
      "faithfulness": 0.7692307692307693,
      "answer_relevancy": 0.8181818181818182,
      "context_recall": 0.15104166666666666
    },
    {
      "context_precision": 0.07972759425088419,
      "faithfulness": 0.0,
      "answer_relevancy": 0.0,
      "context_recall": 0.18556701030927836
    }
  ],
  "detailed_logs": [
    {
      "sample_id": 1,
      "question": "What is the name of the character in Quantico played by the same actor who starred in Tower Block?"
    },
    {
      "sample_id": 2,
      "question": "Which composer was Hungarian, Béla Bartók or Johann Christoph Pepusch?"
    },
    {
      "sample_id": 3,
      "question": "Which American guitarist and bluegrass musician from Danville, Virginia did Rebecca Rippy play or sh..."
    },
    {
      "sample_id": 4,
      "question": "Logan Lerman starred in which 2017 drama directed by Shawn Christensen?"
    },
    {
      "sample_id": 5,
      "question": "Which film was released first, Roving Mars or The London Connection?"
    },
    {
      "sample_id": 6,
      "question": "Splendor in the Grass was a film directed by a Greek-American director described as  \"one of the mos..."
    },
    {
      "sample_id": 7,
      "question": "Who administers the federal law that the California Healthy Families Program implements?"
    },
    {
      "sample_id": 8,
      "question": "The actress that plays Amber in the sitcom \"The Old Guys\" received a BAFTA TV Award in 2014 for her ..."
    },
    {
      "sample_id": 9,
      "question": "Who was the former wife of the American musician who led the band Kings of Rhythm?"
    },
    {
      "sample_id": 10,
      "question": "Which star in The Pokrovsky Gate was also a director and occasional singer?"
    },
    {
      "sample_id": 11,
      "question": "When was the English disc jockey who hosted \"The Voice UK\" born? "
    },
    {
      "sample_id": 12,
      "question": "6 Interpretations included the songwriter who performed in what band from 1985 to 1995?"
    },
    {
      "sample_id": 13,
      "question": "Feodor Chin voices the character of Zenyatta from a game by a developer an publisher based in what c..."
    },
    {
      "sample_id": 14,
      "question": "Pete Mount was the father of the American Basketball Player who was the first high school athlete on..."
    },
    {
      "sample_id": 15,
      "question": "John Martin & Co. is responsible for the pageant that has been known as what since 1996?"
    },
    {
      "sample_id": 16,
      "question": "Who directed Revolver, the 2005 crime thriller starring the English actor Jason Statham?"
    },
    {
      "sample_id": 17,
      "question": "Which painter created the 'Beguiling of Merlin' and was closely associated with the later part of th..."
    },
    {
      "sample_id": 18,
      "question": "In what conference is the University that had a coach born on September 9th, 1960?"
    },
    {
      "sample_id": 19,
      "question": " \"Your Love Had Taken Me That High\" is a song recorded by a singer that received a string of Country..."
    },
    {
      "sample_id": 20,
      "question": "Who replaced the Peabody Award winner, made famous for his NPR flagship program, in 2004?"
    },
    {
      "sample_id": 21,
      "question": "Arthur bell as an amateur cricketer player for what league known for employing professional players."
    },
    {
      "sample_id": 22,
      "question": "In regards to the album that had, according to Dave Grohl, his favourite song he has ever written, w..."
    },
    {
      "sample_id": 23,
      "question": "True Williams was the first to illustrate which title character of a Mark Twain novel?"
    },
    {
      "sample_id": 24,
      "question": "KKWQ-FM is a local radio station covering which area, that is a coextensive with Angle Township?"
    },
    {
      "sample_id": 25,
      "question": "When did the British/Irish digital television channel, which features Spliced, first launch?"
    },
    {
      "sample_id": 26,
      "question": "In which school was the fictional character in \"The Simpsons\" which was voice by Marcia Wallace a te..."
    },
    {
      "sample_id": 27,
      "question": "Which author is known for her \"Anne of Green Gables\" books: Lucy Maud Montgomery or Jan Karon?"
    },
    {
      "sample_id": 28,
      "question": "Which award did the star of The Nativity Story win at the 2004 Broadcast Film Critics Association Aw..."
    },
    {
      "sample_id": 29,
      "question": "La Valentina starred the actress who was the second wife of which actor?"
    },
    {
      "sample_id": 30,
      "question": "Who was the director of the film which had \"Held\" on its soundtrack?"
    },
    {
      "sample_id": 31,
      "question": "What was the 2013 population of the country Fujairah College is located in?"
    },
    {
      "sample_id": 32,
      "question": "What is the instrument played by the instrumentalist with whom Taj Mahal and N. Ravikiran made Mumta..."
    },
    {
      "sample_id": 33,
      "question": "What is the Soninke language meaning of the name of the democracy that is home to Kumasi Airport?"
    },
    {
      "sample_id": 34,
      "question": "Shere Khan is a fictional Bengal tiger that was the main antagonist in Rudyard Kipling's book titled..."
    },
    {
      "sample_id": 35,
      "question": "Makers: Women Who Make America featured an interview with what talk who host, who was dubbed the \"Qu..."
    },
    {
      "sample_id": 36,
      "question": "Mathilde Ludendorff was the wife of the German General who was victorious at which two battles?"
    },
    {
      "sample_id": 37,
      "question": " Hariharan Pillai Happy Aanu contains music by which arranger from Kerala?"
    },
    {
      "sample_id": 38,
      "question": "Who is the current head coach of the basketball team for which Michael Beasley played for one year b..."
    },
    {
      "sample_id": 39,
      "question": "What was the franchise, in which Anton Šťastný played 9 seasons, renamed after moving in 1995?"
    },
    {
      "sample_id": 40,
      "question": "The actor that uses the stage name \"Li Ming\" starred with Donnie Yen in a 2005 Hong Kong film direct..."
    },
    {
      "sample_id": 41,
      "question": "What 1982 film, aired in 1983, was the seventh highest rated non-sports show and featured Kansas sta..."
    },
    {
      "sample_id": 42,
      "question": "The author of \"Evolution: A Theory in Crisis\" is a Senior Fellow at what institute?"
    },
    {
      "sample_id": 43,
      "question": "What college did the Chiefs all time leading rusher attend?"
    },
    {
      "sample_id": 44,
      "question": "When was the American rapper from Atlanta, Georgia born who's song is \"Sneakin'\"?"
    },
    {
      "sample_id": 45,
      "question": "Who was born in 1976 and co-wrote the teleplay for the first episode of \"Black Mirror?\""
    },
    {
      "sample_id": 46,
      "question": "Statistician Walter Francis Willcox received three degrees from a local college in Massachusetts. Wh..."
    },
    {
      "sample_id": 47,
      "question": "Who was the head coach of the Duke Blue Devils football team when they played at Wallace Wade Stadiu..."
    },
    {
      "sample_id": 48,
      "question": "Which jury member for Deutschland sucht den Superstar was an American model and choreographer born i..."
    },
    {
      "sample_id": 49,
      "question": " Meg is an upcoming American film staring a former what?"
    },
    {
      "sample_id": 50,
      "question": "How long is the river on which Wilbur Dam is located?"
    },
    {
      "sample_id": 51,
      "question": "What is the busiest Amtrak route that does not stop at either Lortorn Station?"
    },
    {
      "sample_id": 52,
      "question": "A radio comedy broadcast on BBC Radio 4 that satirizes the week's news, in its early days featured t..."
    },
    {
      "sample_id": 53,
      "question": " Portrait of Wally is a 1912 oil painting by a protégé of Gustav Klimt whose work is noted for its i..."
    },
    {
      "sample_id": 54,
      "question": "Stephen Williams is head coach of which Lutheran school located in Adelaide, South Australia?"
    },
    {
      "sample_id": 55,
      "question": "What is the birthdate of this former NASA astronaut and a retired captain in the United States Navy,..."
    },
    {
      "sample_id": 56,
      "question": "What is a small network appliance and entertainment device that serves as a the media player for the..."
    },
    {
      "sample_id": 57,
      "question": "Which part of SOKOM was formerly of the Royal Danish Army?"
    },
    {
      "sample_id": 58,
      "question": "Who developed the game with whom the man who created the C programming language was incorrectly cite..."
    },
    {
      "sample_id": 59,
      "question": "What author who wrote \"Jesus' Son\" beat out Mischa Berlinksi for 2007 National Book Award?"
    },
    {
      "sample_id": 60,
      "question": "Who directed the 2004 film that featured \"Más\" by Kinky?"
    },
    {
      "sample_id": 61,
      "question": "What king to whom Rev James MacGregor was made chaplain died in 1936?"
    },
    {
      "sample_id": 62,
      "question": "With which division of the Southeastern Conference the football program compete in which  Damontre L..."
    },
    {
      "sample_id": 63,
      "question": "This footballer played in the top divisions in Italy, Spain, England and Germany and is known for wh..."
    },
    {
      "sample_id": 64,
      "question": "Moment by Moment was from the movie that starred which actress, comedian, and producer?"
    },
    {
      "sample_id": 65,
      "question": "What music magazine ran from 1942 to 2008 and had a compilation album \"The Wild Bunch\" in 1984?"
    },
    {
      "sample_id": 66,
      "question": "Hunter Mountain is the second highest peak in the Catskills, in the south east area of which U.S. St..."
    },
    {
      "sample_id": 67,
      "question": "What dancer who died August 9, 2003 appeared in White Nights?"
    },
    {
      "sample_id": 68,
      "question": "Diane Roark was wrongly suspected of leaking information to a New York Times reporter that has co-wr..."
    },
    {
      "sample_id": 69,
      "question": "Alain Fossoul played this position whose primary role is to prevent the opposing team from what"
    },
    {
      "sample_id": 70,
      "question": "Which institute is this American football coach currently serving as head coach, who led 2013 Boise ..."
    },
    {
      "sample_id": 71,
      "question": "What is the name of the Tindersticks' soundtrack for which the film, written by Denis and Jean-Pol F..."
    },
    {
      "sample_id": 72,
      "question": "Terry Pratchett's The Colour of Magic starred which star of Only Fools and Horses?"
    },
    {
      "sample_id": 73,
      "question": "Which  British politician from Northern Ireland who is a Democratic Unionist Party Member of Parliam..."
    },
    {
      "sample_id": 74,
      "question": "What type of a scholar was the rabbi who asked Rabbi Dovid Povarsky to join the previous two heads o..."
    },
    {
      "sample_id": 75,
      "question": "Produced by Jay Joyce, Celabraison is the debut album for which band?"
    },
    {
      "sample_id": 76,
      "question": "The university where Peter Charanis was the Voorhees Professor of History is in what state?"
    },
    {
      "sample_id": 77,
      "question": "Which television show premiered in 2008 and featured a contestant who previously starred in \"Hannah ..."
    },
    {
      "sample_id": 78,
      "question": "Who founded the knighthood in which Gino Cassinis was part of?"
    },
    {
      "sample_id": 79,
      "question": "The former 10th congressional district of Minnesota is now currently represented by whom in the US H..."
    },
    {
      "sample_id": 80,
      "question": "The 2017 Supercheap Auto Bathurst 1000 will be held at the racing track with what two official names..."
    },
    {
      "sample_id": 81,
      "question": "Which original attraction at Universal Studios Florida, featuring Yogi Bear and Boo Boo, was replace..."
    },
    {
      "sample_id": 82,
      "question": "Roy Browns running mate in the 2008 Montana gubernatorial election won his current senate seat by de..."
    },
    {
      "sample_id": 83,
      "question": "Who was the drummer for the recording of \"The Man Who Sold the World\" released in the US in 1970?"
    },
    {
      "sample_id": 84,
      "question": "Who directed the 2013 slasher film that Alexandra Daddario starred in?"
    },
    {
      "sample_id": 85,
      "question": "Where does this Argentine sports club currently compete that Augusto Solari currently is a professio..."
    },
    {
      "sample_id": 86,
      "question": "who voiced the  cartoon character in the animated television series which , Pablo Aurrecochea wears ..."
    },
    {
      "sample_id": 87,
      "question": "Arlette Roxburgh is best known for singing a national anthem whose lyrics come from what poem, befor..."
    },
    {
      "sample_id": 88,
      "question": "A Mars crater is named after the successor of who?"
    },
    {
      "sample_id": 89,
      "question": "Which 2004 novel by Judith Guest recounts the murder committed by John Norman Collins known as the M..."
    },
    {
      "sample_id": 90,
      "question": "What is the country whose capital and largest city is the birth place of this American musician and ..."
    },
    {
      "sample_id": 91,
      "question": "What British man was was wrongly convicted of murdering Jill Dando?"
    },
    {
      "sample_id": 92,
      "question": "Which is the progenitor of the dingo, the Indian pariah dog or the Anglo-Français de Petite Vénerie?"
    },
    {
      "sample_id": 93,
      "question": "What American luxury jewelry and specialty retailer did Jean Michel Schlumberger work at?"
    },
    {
      "sample_id": 94,
      "question": "What mosaic inside the main church of Florence is attributed to Gaddo Gaddi?"
    },
    {
      "sample_id": 95,
      "question": "The company that manufactured PDQ Chocolate is a registered trademark of what company?"
    },
    {
      "sample_id": 96,
      "question": "Who is this retired American politician who was a U. S. representative of Oklahoma's 2nd Congression..."
    },
    {
      "sample_id": 97,
      "question": "Frederic de Hoffmann assisted which Hungarian-American physicist in the development of the hydrogen ..."
    },
    {
      "sample_id": 98,
      "question": "What character did Pam Ferris play in the film based on a J.K Rowling novel?"
    },
    {
      "sample_id": 99,
      "question": "The Office of the Federal Register is an office of the United States government within which indepen..."
    },
    {
      "sample_id": 100,
      "question": "To which film category are both Call Me Kuchu and That's Dancing! belong?"
    },
    {
      "sample_id": 101,
      "question": "The Crocs River is a tributary of a river given what nickname?"
    },
    {
      "sample_id": 102,
      "question": "\"Yaamirukka Bayamey\" is based on which 1998 Korean film directed by Kim Jee-woon?"
    },
    {
      "sample_id": 103,
      "question": "What kind of activity are the niche-themed products Bookchase and San Marco?"
    },
    {
      "sample_id": 104,
      "question": "On which novel is the 1965 film with a character Agent Zeke Kelso based?"
    },
    {
      "sample_id": 105,
      "question": "During Which debt crises did PIGS  used to refer to the economies of Portugal, Ireland, Greece, and ..."
    },
    {
      "sample_id": 106,
      "question": "What caucus is the current Representative from Texas's 6th congressional district a member of?"
    },
    {
      "sample_id": 107,
      "question": "What is the French name of the bay into which the Big Salon River flows?"
    },
    {
      "sample_id": 108,
      "question": "Ray Winstone appeared in what 2005 French-British computer-animated adventure fantasy that was based..."
    },
    {
      "sample_id": 109,
      "question": "What is the city that Victor Estrada was born in officially know as?"
    },
    {
      "sample_id": 110,
      "question": "Who developed the game which Folkenstal features weapons and armors in a cosplay? "
    },
    {
      "sample_id": 111,
      "question": "A 2005 French-language Canadian coming of age drama features artists including an American country m..."
    },
    {
      "sample_id": 112,
      "question": "What high school did NFL quarterback, Heisman winner, and OU football player graduate from?"
    },
    {
      "sample_id": 113,
      "question": "What actress starred with James Franco in Palo Alto and played Kristina Jung in \"Blow\"?"
    },
    {
      "sample_id": 114,
      "question": "Which television series did Deborah Ann Woll play in that was a spin-off of Marvel's Daredevil?"
    },
    {
      "sample_id": 115,
      "question": "What Golden Globe nominated American actor from Juilliard School played a role in the 1986 romantic ..."
    },
    {
      "sample_id": 116,
      "question": "Lynyrd Skynyrd lost three members in a crash of a plane that was chartered from which company?"
    },
    {
      "sample_id": 117,
      "question": "What county in Nevada contains both the City of Las Vegas and the College of Southern Nevada?"
    },
    {
      "sample_id": 118,
      "question": "The Genève-Servette HC competes in a league know by what name prior to the 2017-2018 season?"
    },
    {
      "sample_id": 119,
      "question": "Which Norwegian actress performed in Anton Checkhov's \"Three Sisters\" as well as a three-act play wr..."
    },
    {
      "sample_id": 120,
      "question": "Which of these has its entrance in Piyer Loti Caddesi, Hagia Sophia or Theodosius Cistern?"
    },
    {
      "sample_id": 121,
      "question": "Waht kind of music do the bands Nada Surf and Madina Lake play?"
    },
    {
      "sample_id": 122,
      "question": "What was the screenplay novelist, Caroline Thompson, base in an Victorian era village for Victor and..."
    },
    {
      "sample_id": 123,
      "question": "What was the job title of this American engineer and former astronaut aboard Apollo 11, who inspired..."
    },
    {
      "sample_id": 124,
      "question": "The song \"Good Life\" recorded by G-Eazy and Kehlani appeared on the soundtrack for what  2017 action..."
    },
    {
      "sample_id": 125,
      "question": "When was the 15th pick of the 2011 NFL born ?"
    },
    {
      "sample_id": 126,
      "question": "Which man, Ben Bagdikian or Eddie Mekka, is most famous for his role as Carmine \"The Big Ragu\" Ragus..."
    },
    {
      "sample_id": 127,
      "question": "The 2016 Baylor Bears football team were invited to what event when they defeated the 2016 Boise Sta..."
    },
    {
      "sample_id": 128,
      "question": "The sauce that fills a BiFi Carazza is referred to as what by Italians?"
    },
    {
      "sample_id": 129,
      "question": "What is the urdu name of Afghan citizens living as refugee in a country other than Iran?"
    },
    {
      "sample_id": 130,
      "question": "Into the Labyrinth was only was later shown in the United States as part of a program whose featuret..."
    },
    {
      "sample_id": 131,
      "question": "Talking Smack is an American talk show whose past hosts have included the current Intercontinental C..."
    },
    {
      "sample_id": 132,
      "question": "When did the event Rue d'Alésia is named for take place?"
    },
    {
      "sample_id": 133,
      "question": "Eric Jacobson performed the Muppet character who was part of what fictional band?"
    },
    {
      "sample_id": 134,
      "question": "When was the by-election of a constituency represented in the House of Commons of the UK Parliament ..."
    },
    {
      "sample_id": 135,
      "question": "Lucy Elizabeth Fry played the lead in a television series that follows Eve who is a 19-year-old what..."
    },
    {
      "sample_id": 136,
      "question": "At which age Audrey Kathryn Lindvall's super model sister was discover by IMG scout?"
    },
    {
      "sample_id": 137,
      "question": "What is the nickname of the host for which \"Winner Take All\" is best known?"
    },
    {
      "sample_id": 138,
      "question": "BLIZZARD! The Storm That Changed America was about the storm also referred to as what?"
    },
    {
      "sample_id": 139,
      "question": "Emilio Botin was a banker that ran an institution that merged with what group?"
    },
    {
      "sample_id": 140,
      "question": "Which actress, model, and singer born in 1926 does the film Golden Hoofs star?"
    },
    {
      "sample_id": 141,
      "question": "Where was the actress who starred in Trishna with Riz Ahmed born?"
    },
    {
      "sample_id": 142,
      "question": "The song \"Boom\" features an artist born on January 17, 1971 with what legal name?"
    },
    {
      "sample_id": 143,
      "question": "When was the director of King of the Dancehall born?"
    },
    {
      "sample_id": 144,
      "question": "WERT is a radio station that is broadcast from it studios on what transcontinental highway?"
    },
    {
      "sample_id": 145,
      "question": "What show created by Michael G. Moye and Ron Leavitt aired on May 2, 2006 in Chile? "
    },
    {
      "sample_id": 146,
      "question": "What film company produced The Littlest Outlaw and The Jungle Book?"
    },
    {
      "sample_id": 147,
      "question": "Westfield Culver City is owned by what Australian shopping centre company that existed from 1960 to ..."
    },
    {
      "sample_id": 148,
      "question": "The Chase is hosted by an actress who began her television career in what Spanish-American teen sitc..."
    },
    {
      "sample_id": 149,
      "question": "Which author of Superman: The Wedding Album is known for creating the superhero Booster Gold?"
    },
    {
      "sample_id": 150,
      "question": "The Wrekin is a hill that can be seen even as far as a landmark 47-storey mixed use skyscraper that ..."
    },
    {
      "sample_id": 151,
      "question": "Party Never Ends is an album by the Romanian singer who studied at what college?"
    },
    {
      "sample_id": 152,
      "question": "Which star of Don 2 was named by \"Time\" magazine as one of the 100 most influential people in the wo..."
    },
    {
      "sample_id": 153,
      "question": "Who composed the original score and songs of the film based on the play \"The Man Who Was Peter Pan\" ..."
    },
    {
      "sample_id": 154,
      "question": "Team Halfords Bikehut was the team of the British female cyclist who now works in what capacity?"
    },
    {
      "sample_id": 155,
      "question": "A television show originaly aired on December 29, 1996 was written by a graduate of what University?"
    },
    {
      "sample_id": 156,
      "question": "When was the American fitness guru, actor, and comedian born who is known for his eccentric, flamboy..."
    },
    {
      "sample_id": 157,
      "question": "When was American actor who acted Spock in The City on the Edge of Forever born? "
    },
    {
      "sample_id": 158,
      "question": "Which dog is now extinct, the Tahltan Bear Dog or the Stichelhaar?"
    },
    {
      "sample_id": 159,
      "question": "In which city was the American alternative rock band who released the single Blinded formed?"
    },
    {
      "sample_id": 160,
      "question": "What 2014 American 3D computer-animated musical fantasy adventure comedy film features a song record..."
    },
    {
      "sample_id": 161,
      "question": "Which stadium in Orlando opened in 1936 and is found west of the home venue for the Orlando City SC?"
    },
    {
      "sample_id": 162,
      "question": "Who was the director of the 2004 French action film for which Tony D'Amario is best known?"
    },
    {
      "sample_id": 163,
      "question": "Where was the captain that the USS Elrod is named after born?"
    },
    {
      "sample_id": 164,
      "question": "Aspects of Andrew Lloyd Webber is the second studio album by a singer that played what role in theAu..."
    },
    {
      "sample_id": 165,
      "question": "Which American distance runner who died in an automobile accident in Oregon had a trail named after ..."
    },
    {
      "sample_id": 166,
      "question": "Manfred Moch was the featured solo trumpet player of the orchestra named after which German orchestr..."
    },
    {
      "sample_id": 167,
      "question": "Which TV show starring Will Smith was written by the creator of \"The Borowitz Report\"?"
    },
    {
      "sample_id": 168,
      "question": "What politician from New York served two terms representing New York in the United States Senate? "
    },
    {
      "sample_id": 169,
      "question": "John Still was a British archaeologist known for his discoveries at an ancient rock fortress located..."
    },
    {
      "sample_id": 170,
      "question": "What 2016 animated movie about birds, written by Jon Vitti, features characters also used in a pinba..."
    },
    {
      "sample_id": 171,
      "question": "Which topic in the Dear America series took place in New York City?"
    },
    {
      "sample_id": 172,
      "question": "What country does Florida Board of Regents and State University System of Florida have in common?"
    },
    {
      "sample_id": 173,
      "question": "Where was the Hockey League which drafted Niclas Bergfors based?"
    },
    {
      "sample_id": 174,
      "question": "Which person included in the label 300 Entertainment has a debut single \"Trap Queen?\""
    },
    {
      "sample_id": 175,
      "question": "Whitechapel is a series that depicted a killer who was copying the actions of which unidentified ser..."
    },
    {
      "sample_id": 176,
      "question": "What star of the 1994 film Krantiveer was born January 1, 1951?"
    },
    {
      "sample_id": 177,
      "question": "Federalist No. 7 was written by which of the Founding Fathers?"
    },
    {
      "sample_id": 178,
      "question": "Which song is sampled in \"Sugar\", a song from the 2015 album of the same name by Robin Schulz?"
    },
    {
      "sample_id": 179,
      "question": "Which band was discovered by the man that recruited Peter Brown for their management team?"
    },
    {
      "sample_id": 180,
      "question": "Which is a correspondent for NBC, Janet Shamlian or Mia Tyler?"
    },
    {
      "sample_id": 181,
      "question": "What was the number one single by the band that features a lead singer who won the season finale of ..."
    },
    {
      "sample_id": 182,
      "question": "Which racing circuit is the venue for the FIA Formula One Canadian Grand Prix and is home to the fir..."
    },
    {
      "sample_id": 183,
      "question": "What William Shakespeare play was written in 1599 and based on true events in Roman history?"
    },
    {
      "sample_id": 184,
      "question": "This voice actor stared as Hanna-Barbera's cartoon character Space Ghost in its American adult anima..."
    },
    {
      "sample_id": 185,
      "question": "Henry Gabriel Cisneros followed what Texas Revolutionary figure as a Latino mayer of a major America..."
    },
    {
      "sample_id": 186,
      "question": "At what school is the \"A Real Young Girl\" director a professor at?"
    },
    {
      "sample_id": 187,
      "question": "Which child actress began her career in 2006 and also stared in the television series The Emperor: O..."
    },
    {
      "sample_id": 188,
      "question": "Silver City is a band that is an example of which genre, also known as avant-rock?"
    },
    {
      "sample_id": 189,
      "question": "Return to House on Haunted Hill is a sequel to a 1999 horror film directed by whom?"
    },
    {
      "sample_id": 190,
      "question": "Who is the director of the upcoming Candian drama film in which the actress who made her film début ..."
    },
    {
      "sample_id": 191,
      "question": "What american actor who was in the film Like Mike, also played in 2012 American military science fic..."
    },
    {
      "sample_id": 192,
      "question": "What were the professions of the host of the documentary \"Anti-Semitism in the 21st Century: The Res..."
    },
    {
      "sample_id": 193,
      "question": "What was the original name of the gazette that publishes Lytham St Annes Express?"
    },
    {
      "sample_id": 194,
      "question": "Derrick Delite's rap was featured on the remix and video version of a song by an American singer tha..."
    },
    {
      "sample_id": 195,
      "question": "Who has a wider scope of profession, Natalie Merchant or Marian Gold?"
    },
    {
      "sample_id": 196,
      "question": "Who directed the 2017 film in which Kim Hyang-gi starred?"
    },
    {
      "sample_id": 197,
      "question": "John D. Rockefeller III was the older brother of which chief executive of Chase Manhattan Corporatio..."
    },
    {
      "sample_id": 198,
      "question": "What member of Slam Creepers made a version of “Hooked on a Feeling”"
    },
    {
      "sample_id": 199,
      "question": "Walls Have Eyes was produced by a member of what band?"
    },
    {
      "sample_id": 200,
      "question": "Who is the founder and head of brewing company based in Milton, Delaware?"
    }
  ],
  "experiment_config": {
    "batch_id": 2,
    "experiment_type": "baseline",
    "batch_size": 200,
    "processed_samples": 200,
    "error_count": 0
  }
}